top.v
module top (
    input clk,
    input reset,
    output reg [31:0] pc,
    output reg [31:0] alu_result
);

    // Internal "wires"
    reg [31:0] instruction;
    
    // 1. Simple Program Counter Logic
    always @(posedge clk or posedge reset) begin
        if (reset) begin
            pc <= 0;
            instruction <= 0;
        end else begin
            pc <= pc + 4;
            // Fake instruction fetch: just making up data based on PC
            // In real life, this comes from an Instruction Memory array
            instruction <= (pc == 0) ? 32'h00500113  // ADDI x2, x0, 5
                         : (pc == 4) ? 32'h00a00193  // ADDI x3, x0, 10
                         : 32'h00000000;             // NOP
        end
    end

    // 2. Simple ALU (Combinational Logic)
    // Let's pretend we are just adding PC + 42 for this demo
    always @(*) begin
        alu_result = pc + 42;
    end

endmodule

waveform.vcd
$version Generated by VerilatedVcd $end
$timescale 1ps $end
 $scope module TOP $end
  $var wire 1 # clk $end
  $var wire 1 $ reset $end
  $var wire 32 % pc [31:0] $end
  $var wire 32 & alu_result [31:0] $end
  $scope module top $end
   $var wire 1 # clk $end
   $var wire 1 $ reset $end
   $var wire 32 % pc [31:0] $end
   $var wire 32 & alu_result [31:0] $end
   $var wire 32 ' instruction [31:0] $end
  $upscope $end
 $upscope $end
$enddefinitions $end


#0
0#
1$
b00000000000000000000000000000000 %
b00000000000000000000000000101010 &
b00000000000000000000000000000000 '
#1
1#
0$
b00000000000000000000000000000100 %
b00000000000000000000000000101110 &
b00000000010100000000000100010011 '
#2
0#
#3
1#
b00000000000000000000000000001000 %
b00000000000000000000000000110010 &
b00000000101000000000000110010011 '
#4
0#
#5
1#
b00000000000000000000000000001100 %
b00000000000000000000000000110110 &
b00000000000000000000000000000000 '
#6
0#
#7
1#
b00000000000000000000000000010000 %
b00000000000000000000000000111010 &
#8
0#
#9
1#
b00000000000000000000000000010100 %
b00000000000000000000000000111110 &
#10
0#
#11
1#
b00000000000000000000000000011000 %
b00000000000000000000000001000010 &
#12
0#
#13
1#
b00000000000000000000000000011100 %
b00000000000000000000000001000110 &
#14
0#
#15
1#
b00000000000000000000000000100000 %
b00000000000000000000000001001010 &
#16
0#
#17
1#
b00000000000000000000000000100100 %
b00000000000000000000000001001110 &
#18
0#
#19
1#
b00000000000000000000000000101000 %
b00000000000000000000000001010010 &
